{
  "BTC": {
    "label": "LONG_moderate",
    "bias": "LONG CROWDED",
    "signal": "PARZIALE",
    "ts": 1783192985,
    "since_ts": 1783026937,
    "confluence": {
      "score": 10,
      "total": 17
    },
    "data": {
      "price": 63222.3,
      "px24h": 1.6788788389537224,
      "px4h": 0.498340454753548,
      "oi24h": -1.7793958675651895,
      "oi4h": -0.2874072506303396,
      "funding": 0.9480000000000001,
      "lsr": 1.5214,
      "lsrSource": "coinalyze",
      "trend": {
        "label": "TREND UP",
        "emaFast": 62257.63638416829,
        "emaSlow": 61226.37134450568,
        "emaMacro": 61226.37134450568,
        "emaMacroPeriod": 50,
        "fastVsSlow": true,
        "aboveMacro": true
      },
      "obv": {
        "obvChange": -11.072649204374894,
        "priceChange": 4.918353605344246,
        "diverge": true,
        "direction": -1
      },
      "rvol": {
        "ratio": 0.6005127525528496,
        "current": 17869.203000000638,
        "avg": 29756.575400000373
      },
      "fvg": {
        "above": null,
        "below": {
          "type": "bull",
          "top": 62752.9,
          "bottom": 62654.1,
          "size": 0.15769119658570294,
          "distance": -0.7424595435471367
        },
        "count": 5
      },
      "poc": {
        "poc": 60275.252,
        "vah": 63646.615999999995,
        "val": 58233.439999999995,
        "rangeHigh": 67255.4,
        "rangeLow": 57758.6,
        "distance": -4.6614058647028065,
        "inValueArea": true
      },
      "vwapW": {
        "vwap": 60270.26156824733,
        "distance": 4.964203495889473,
        "above": true,
        "bars": 42
      },
      "vwapM": {
        "vwap": 61945.69645170863,
        "distance": 2.1252542528401155,
        "above": true,
        "bars": 130
      },
      "delta": {
        "lastDelta": 1674.1110000000517,
        "cumDelta": 4249.850999999984,
        "ratio": 0.10416715841416478,
        "bars": 3
      }
    }
  },
  "ETH": {
    "label": "LONG_moderate",
    "bias": "LONG CROWDED",
    "signal": "PIATTO",
    "ts": 1783192985,
    "since_ts": 1782997495,
    "confluence": {
      "score": 9,
      "total": 17
    },
    "data": {
      "price": 1791.7,
      "px24h": 2.6891642499340933,
      "px4h": 0.07093268097607736,
      "oi24h": 0.24034912560411092,
      "oi4h": -0.8741321172006971,
      "funding": 0.5166999999999999,
      "lsr": 1.6035,
      "lsrSource": "coinalyze",
      "trend": {
        "label": "TREND UP",
        "emaFast": 1743.6051902077131,
        "emaSlow": 1668.0309618847875,
        "emaMacro": 1668.0309618847875,
        "emaMacroPeriod": 50,
        "fastVsSlow": true,
        "aboveMacro": true
      },
      "obv": {
        "obvChange": 95.4593434026188,
        "priceChange": 13.601423397411555,
        "diverge": false,
        "direction": 1
      },
      "rvol": {
        "ratio": 0.8797827253968951,
        "current": 698289.4589999963,
        "avg": 793706.7174000012
      },
      "fvg": {
        "above": null,
        "below": {
          "type": "bull",
          "top": 1778.08,
          "bottom": 1765.42,
          "size": 0.7171098095637216,
          "distance": -0.7601719037785409
        },
        "count": 5
      },
      "poc": {
        "poc": 1576.76245,
        "vah": 1737.2696999999998,
        "val": 1548.0401,
        "rangeHigh": 1848.78,
        "rangeLow": 1510.87,
        "distance": -11.99629123179104,
        "inValueArea": false
      },
      "vwapW": {
        "vwap": 1637.869684544228,
        "distance": 9.54046081506508,
        "above": true,
        "bars": 42
      },
      "vwapM": {
        "vwap": 1672.289658622162,
        "distance": 7.285839552355129,
        "above": true,
        "bars": 130
      },
      "delta": {
        "lastDelta": 20013.198999996064,
        "cumDelta": 76605.65799999598,
        "ratio": 0.04160042356399278,
        "bars": 3
      }
    }
  },
  "SOL": {
    "label": "LONG_moderate",
    "bias": "LONG CROWDED",
    "signal": "CONFERMA",
    "ts": 1783192985,
    "since_ts": 1783049898,
    "confluence": {
      "score": 9,
      "total": 17
    },
    "data": {
      "price": 81.84,
      "px24h": -0.7398423286840502,
      "px4h": -0.4258425599221248,
      "oi24h": -1.2580234726566415,
      "oi4h": -1.7192353090838366,
      "funding": 0.48469999999999996,
      "lsr": 1.7778,
      "lsrSource": "coinalyze",
      "trend": {
        "label": "TREND UP",
        "emaFast": 81.47355178165493,
        "emaSlow": 77.06372710487277,
        "emaMacro": 77.06372710487277,
        "emaMacroPeriod": 50,
        "fastVsSlow": true,
        "aboveMacro": true
      },
      "obv": {
        "obvChange": 229.07001449573562,
        "priceChange": 13.732296584282144,
        "diverge": false,
        "direction": 1
      },
      "rvol": {
        "ratio": 0.5213517428091775,
        "current": 2341693.660000008,
        "avg": 4491581.149000019
      },
      "fvg": {
        "above": null,
        "below": {
          "type": "bull",
          "top": 80.03,
          "bottom": 78.68,
          "size": 1.71581087951194,
          "distance": -2.21163245356794
        },
        "count": 2
      },
      "poc": {
        "poc": 73.6806,
        "vah": 75.3772,
        "val": 68.1916,
        "rangeHigh": 83.96,
        "rangeLow": 64.0,
        "distance": -9.969941348973613,
        "inValueArea": false
      },
      "vwapW": {
        "vwap": 76.577867236367,
        "distance": 6.963020721345916,
        "above": true,
        "bars": 42
      },
      "vwapM": {
        "vwap": 72.70801121136185,
        "distance": 12.656086496284443,
        "above": true,
        "bars": 130
      },
      "delta": {
        "lastDelta": -43101.96000002418,
        "cumDelta": -182197.65000007767,
        "ratio": -0.02275329025594679,
        "bars": 3
      }
    }
  },
  "LINK": {
    "label": "NEUTRAL_weak",
    "bias": "LONG CROWDED",
    "signal": "PIATTO",
    "ts": 1783192985,
    "since_ts": 1783157387,
    "confluence": {
      "score": 8,
      "total": 17
    },
    "data": {
      "price": 8.072,
      "px24h": 1.611278952668671,
      "px4h": -0.1484413656605697,
      "oi24h": 2.294455315107168,
      "oi4h": 0.6990984978960848,
      "funding": 1.0,
      "lsr": 2.2489,
      "lsrSource": "coinalyze",
      "trend": {
        "label": "TREND UP",
        "emaFast": 7.893236343330417,
        "emaSlow": 7.623562289317789,
        "emaMacro": 7.623562289317789,
        "emaMacroPeriod": 50,
        "fastVsSlow": true,
        "aboveMacro": true
      },
      "obv": {
        "obvChange": 65.37089801271522,
        "priceChange": 10.17318969044048,
        "diverge": false,
        "direction": 1
      },
      "rvol": {
        "ratio": 0.8705349484319551,
        "current": 1739078.2400000007,
        "avg": 1997712.1460000004
      },
      "fvg": {
        "above": null,
        "below": {
          "type": "bull",
          "top": 8.052,
          "bottom": 7.944,
          "size": 1.359516616314195,
          "distance": -0.24777006937561416
        },
        "count": 4
      },
      "poc": {
        "poc": 7.930775000000001,
        "vah": 8.44013,
        "val": 7.37291,
        "rangeHigh": 8.618,
        "rangeLow": 7.001,
        "distance": -1.7495664023785755,
        "inValueArea": true
      },
      "vwapW": {
        "vwap": 7.509119767904297,
        "distance": 7.589174892795064,
        "above": true,
        "bars": 42
      },
      "vwapM": {
        "vwap": 7.7130955161498145,
        "distance": 4.7439381903679125,
        "above": true,
        "bars": 130
      },
      "delta": {
        "lastDelta": -16437.500000012806,
        "cumDelta": -182657.8400000143,
        "ratio": -0.03682446686347754,
        "bars": 3
      }
    }
  },
  "ICP": {
    "label": "NEUTRAL_weak",
    "bias": "LONG CROWDED",
    "signal": "PIATTO",
    "ts": 1783192985,
    "since_ts": 1783192985,
    "confluence": {
      "score": 8,
      "total": 17
    },
    "data": {
      "price": 2.263,
      "px24h": 1.5253476895468734,
      "px4h": -0.13239187996470053,
      "oi24h": 3.6787934915613016,
      "oi4h": -0.009443498641574672,
      "funding": 1.0,
      "lsr": 1.2472,
      "lsrSource": "coinalyze",
      "trend": {
        "label": "TREND UP",
        "emaFast": 2.2273182435071393,
        "emaSlow": 2.1980611301744344,
        "emaMacro": 2.1980611301744344,
        "emaMacroPeriod": 50,
        "fastVsSlow": true,
        "aboveMacro": true
      },
      "obv": {
        "obvChange": 22.34756875843416,
        "priceChange": 3.943145346171474,
        "diverge": false,
        "direction": 1
      },
      "rvol": {
        "ratio": 1.3634687327207633,
        "current": 2074662.0,
        "avg": 1521605.85
      },
      "fvg": {
        "above": {
          "type": "bear",
          "top": 2.373,
          "bottom": 2.372,
          "size": 0.04215851602025017,
          "distance": 4.81661511268228
        },
        "below": {
          "type": "bull",
          "top": 2.247,
          "bottom": 2.22,
          "size": 1.2162162162162022,
          "distance": -0.7070260715863904
        },
        "count": 4
      },
      "poc": {
        "poc": 2.180155,
        "vah": 2.3225,
        "val": 2.04943,
        "rangeHigh": 2.613,
        "rangeLow": 2.032,
        "distance": -3.6608484312858964,
        "inValueArea": true
      },
      "vwapW": {
        "vwap": 2.178510098173743,
        "distance": 4.061945909749897,
        "above": true,
        "bars": 42
      },
      "vwapM": {
        "vwap": 2.286959323092665,
        "distance": -0.8727449977411076,
        "above": false,
        "bars": 130
      },
      "delta": {
        "lastDelta": -144336.0,
        "cumDelta": -175275.0,
        "ratio": -0.03140648929473684,
        "bars": 3
      }
    }
  },
  "SUI": {
    "label": "LONG_moderate",
    "bias": "LONG CROWDED",
    "signal": "PIATTO",
    "ts": 1783192985,
    "since_ts": 1783177934,
    "confluence": {
      "score": 8,
      "total": 17
    },
    "data": {
      "price": 0.7729,
      "px24h": 0.5202236961893618,
      "px4h": 0.12955045990413278,
      "oi24h": -0.004586655251622307,
      "oi4h": -0.4964506647970208,
      "funding": 1.0,
      "lsr": 2.4916,
      "lsrSource": "coinalyze",
      "trend": {
        "label": "TREND UP",
        "emaFast": 0.7566593982157634,
        "emaSlow": 0.7269002918498334,
        "emaMacro": 0.7269002918498334,
        "emaMacroPeriod": 50,
        "fastVsSlow": true,
        "aboveMacro": true
      },
      "obv": {
        "obvChange": 69.55191056039075,
        "priceChange": 11.854850368656942,
        "diverge": false,
        "direction": 1
      },
      "rvol": {
        "ratio": 0.9728567189303376,
        "current": 26816583.000000168,
        "avg": 27564781.614999972
      },
      "fvg": {
        "above": null,
        "below": {
          "type": "bull",
          "top": 0.7642,
          "bottom": 0.7601,
          "size": 0.5394027101697135,
          "distance": -1.1256307413637006
        },
        "count": 3
      },
      "poc": {
        "poc": 0.6974965,
        "vah": 0.753598,
        "val": 0.671672,
        "rangeHigh": 0.8284,
        "rangeLow": 0.6503,
        "distance": -9.755919265105456,
        "inValueArea": false
      },
      "vwapW": {
        "vwap": 0.7167378329929837,
        "distance": 7.947420156286632,
        "above": true,
        "bars": 42
      },
      "vwapM": {
        "vwap": 0.7267244718928689,
        "distance": 6.464008014588519,
        "above": true,
        "bars": 130
      },
      "delta": {
        "lastDelta": -1540842.2000002414,
        "cumDelta": -600273.0999998078,
        "ratio": -0.008823354118735973,
        "bars": 3
      }
    }
  },
  "HBAR": {
    "label": "LONG_moderate",
    "bias": "LONG CROWDED",
    "signal": "PIATTO",
    "ts": 1783192985,
    "since_ts": 1783177934,
    "confluence": {
      "score": 8,
      "total": 17
    },
    "data": {
      "price": 0.07482,
      "px24h": 2.916093535075649,
      "px4h": 0.17405275137232723,
      "oi24h": 1.8296518004811624,
      "oi4h": -1.7078285166460399,
      "funding": 1.0,
      "lsr": 0.8182,
      "lsrSource": "coinalyze",
      "trend": {
        "label": "TREND UP",
        "emaFast": 0.07308775566744403,
        "emaSlow": 0.07278483607859412,
        "emaMacro": 0.07278483607859412,
        "emaMacroPeriod": 50,
        "fastVsSlow": true,
        "aboveMacro": true
      },
      "obv": {
        "obvChange": 83.56539996353915,
        "priceChange": 2.3106371342630534,
        "diverge": false,
        "direction": 1
      },
      "rvol": {
        "ratio": 0.8659352208915331,
        "current": 65595989.0,
        "avg": 75751612.15
      },
      "fvg": {
        "above": {
          "type": "bear",
          "top": 0.07826,
          "bottom": 0.07782,
          "size": 0.5654073502955487,
          "distance": 4.009623095429033
        },
        "below": {
          "type": "bull",
          "top": 0.07134,
          "bottom": 0.06953,
          "size": 2.603192866388618,
          "distance": -4.65116279069767
        },
        "count": 3
      },
      "poc": {
        "poc": 0.0717579,
        "vah": 0.0795384,
        "val": 0.06856380000000001,
        "rangeHigh": 0.08478,
        "rangeLow": 0.0684,
        "distance": -4.092622293504408,
        "inValueArea": true
      },
      "vwapW": {
        "vwap": 0.07186926173927413,
        "distance": 4.1196169114228125,
        "above": true,
        "bars": 42
      },
      "vwapM": {
        "vwap": 0.07591221810682168,
        "distance": -1.4256178172778686,
        "above": false,
        "bars": 130
      },
      "delta": {
        "lastDelta": -1565763.0,
        "cumDelta": 5594603.0,
        "ratio": 0.02210559369329718,
        "bars": 3
      }
    }
  },
  "AR": {
    "label": "LONG_moderate",
    "bias": "LONG CROWDED",
    "signal": "PARZIALE",
    "ts": 1783192985,
    "since_ts": 1783192985,
    "confluence": {
      "score": 9,
      "total": 17
    },
    "data": {
      "price": 2.115,
      "px24h": 4.8067393458870376,
      "px4h": 1.4388489208633213,
      "oi24h": 3.5852584533643324,
      "oi4h": 1.33738416937458,
      "funding": 1.0,
      "lsr": 1.624,
      "lsrSource": "coinalyze",
      "trend": {
        "label": "TREND UP",
        "emaFast": 2.0457238950362204,
        "emaSlow": 1.9830414062114496,
        "emaMacro": 1.9830414062114496,
        "emaMacroPeriod": 50,
        "fastVsSlow": true,
        "aboveMacro": true
      },
      "obv": {
        "obvChange": 88.9572754968159,
        "priceChange": 12.129237288135599,
        "diverge": false,
        "direction": 1
      },
      "rvol": {
        "ratio": 1.891659949143815,
        "current": 743437.9000000013,
        "avg": 393008.21499999985
      },
      "fvg": {
        "above": null,
        "below": {
          "type": "bull",
          "top": 2.049,
          "bottom": 2.024,
          "size": 1.235177865612644,
          "distance": -3.1205673758865378
        },
        "count": 3
      },
      "poc": {
        "poc": 2.006585,
        "vah": 2.07781,
        "val": 1.9109399999999999,
        "rangeHigh": 2.147,
        "rangeLow": 1.74,
        "distance": -5.126004728132405,
        "inValueArea": false
      },
      "vwapW": {
        "vwap": 1.9813465001019313,
        "distance": 6.846530876406019,
        "above": true,
        "bars": 42
      },
      "vwapM": {
        "vwap": 1.978416113146898,
        "distance": 7.0047896361230295,
        "above": true,
        "bars": 130
      },
      "delta": {
        "lastDelta": 273.89999999734573,
        "cumDelta": 28043.09999999602,
        "ratio": 0.014366643235504264,
        "bars": 3
      }
    }
  },
  "TAO": {
    "label": "NEUTRAL_weak",
    "bias": "LONG CROWDED",
    "signal": "PARZIALE",
    "ts": 1783192985,
    "since_ts": 1783049898,
    "confluence": {
      "score": 6,
      "total": 17
    },
    "data": {
      "price": 217.24,
      "px24h": 1.2254787754531455,
      "px4h": 1.0888785481619372,
      "oi24h": 0.5386226228040408,
      "oi4h": -0.2183953607088973,
      "funding": 0.5,
      "lsr": 1.1561,
      "lsrSource": "coinalyze",
      "trend": {
        "label": "TREND UP",
        "emaFast": 213.53623129742675,
        "emaSlow": 212.35092001175406,
        "emaMacro": 212.35092001175406,
        "emaMacroPeriod": 50,
        "fastVsSlow": true,
        "aboveMacro": true
      },
      "obv": {
        "obvChange": -35.0503006811447,
        "priceChange": 1.9722664667853365,
        "diverge": false,
        "direction": -1
      },
      "rvol": {
        "ratio": 1.3014306498765973,
        "current": 82129.57800000074,
        "avg": 63107.14904999996
      },
      "fvg": {
        "above": {
          "type": "bear",
          "top": 226.86,
          "bottom": 226.7,
          "size": 0.07057785619762903,
          "distance": 4.354630823052835
        },
        "below": {
          "type": "bull",
          "top": 214.4,
          "bottom": 214.19,
          "size": 0.09804379289416311,
          "distance": -1.307309887681828
        },
        "count": 5
      },
      "poc": {
        "poc": 214.30945,
        "vah": 260.1517,
        "val": 195.49,
        "rangeHigh": 292.0,
        "rangeLow": 195.49,
        "distance": -1.3489918983612645,
        "inValueArea": true
      },
      "vwapW": {
        "vwap": 207.76829501230628,
        "distance": 4.765743968350522,
        "above": true,
        "bars": 42
      },
      "vwapM": {
        "vwap": 240.14483772195118,
        "distance": -9.358867729637982,
        "above": false,
        "bars": 130
      },
      "delta": {
        "lastDelta": -597.7600000009115,
        "cumDelta": -6614.4420000007085,
        "ratio": -0.0397060550785272,
        "bars": 3
      }
    }
  },
  "RENDER": {
    "label": "LONG_moderate",
    "bias": "LONG CROWDED",
    "signal": "PIATTO",
    "ts": 1783192985,
    "since_ts": 1783157387,
    "confluence": {
      "score": 8,
      "total": 17
    },
    "data": {
      "price": 1.613,
      "px24h": 0.5610972568578488,
      "px4h": 0.37336652146857535,
      "oi24h": 1.1107468218836858,
      "oi4h": -0.6716660975961699,
      "funding": 0.2523,
      "lsr": 1.0088,
      "lsrSource": "coinalyze",
      "trend": {
        "label": "TREND UP",
        "emaFast": 1.5945304450547002,
        "emaSlow": 1.576688431565512,
        "emaMacro": 1.576688431565512,
        "emaMacroPeriod": 50,
        "fastVsSlow": true,
        "aboveMacro": true
      },
      "obv": {
        "obvChange": 99.31946044550318,
        "priceChange": 4.737183646982491,
        "diverge": false,
        "direction": 1
      },
      "rvol": {
        "ratio": 1.3241327566990329,
        "current": 2044901.800000004,
        "avg": 1544332.9150000005
      },
      "fvg": {
        "above": {
          "type": "bear",
          "top": 1.654,
          "bottom": 1.628,
          "size": 1.5970515970515984,
          "distance": 0.929944203347793
        },
        "below": {
          "type": "bull",
          "top": 1.603,
          "bottom": 1.594,
          "size": 0.5646173149309848,
          "distance": -0.6199628022318666
        },
        "count": 5
      },
      "poc": {
        "poc": 1.56205,
        "vah": 1.71608,
        "val": 1.4670999999999998,
        "rangeHigh": 1.868,
        "rangeLow": 1.446,
        "distance": -3.1587104773713612,
        "inValueArea": true
      },
      "vwapW": {
        "vwap": 1.5587468843784853,
        "distance": 3.5447137810027263,
        "above": true,
        "bars": 42
      },
      "vwapM": {
        "vwap": 1.6478177028112058,
        "distance": -2.0522720901415292,
        "above": false,
        "bars": 130
      },
      "delta": {
        "lastDelta": -21889.60000000731,
        "cumDelta": 32364.19999999134,
        "ratio": 0.008348615215154375,
        "bars": 3
      }
    }
  },
  "VIRTUAL": {
    "label": "LONG_moderate",
    "bias": "SHORT CROWDED",
    "signal": "PIATTO",
    "ts": 1783192985,
    "since_ts": 1783172646,
    "confluence": {
      "score": 10,
      "total": 17
    },
    "data": {
      "price": 0.5734,
      "px24h": -0.8987210508123025,
      "px4h": -0.33026247175386975,
      "oi24h": -0.7459768175826484,
      "oi4h": -0.7309836726504663,
      "funding": -0.0495,
      "lsr": 0.8986,
      "lsrSource": "coinalyze",
      "trend": {
        "label": "TREND UP",
        "emaFast": 0.5675506563332418,
        "emaSlow": 0.5557631395486026,
        "emaMacro": 0.5557631395486026,
        "emaMacroPeriod": 50,
        "fastVsSlow": true,
        "aboveMacro": true
      },
      "obv": {
        "obvChange": 39.42099759433102,
        "priceChange": 8.363224466679254,
        "diverge": false,
        "direction": 1
      },
      "rvol": {
        "ratio": 0.6684178936280927,
        "current": 3403759.099999991,
        "avg": 5092262.090000003
      },
      "fvg": {
        "above": {
          "type": "bear",
          "top": 0.5926,
          "bottom": 0.5924,
          "size": 0.03376097231599898,
          "distance": 3.3135681897453813
        },
        "below": {
          "type": "bull",
          "top": 0.5696,
          "bottom": 0.5687,
          "size": 0.15825567082820677,
          "distance": -0.6627136379490801
        },
        "count": 5
      },
      "poc": {
        "poc": 0.5308225,
        "vah": 0.607165,
        "val": 0.5123949999999999,
        "rangeHigh": 0.6721,
        "rangeLow": 0.4966,
        "distance": -7.425444715730737,
        "inValueArea": true
      },
      "vwapW": {
        "vwap": 0.5471335723193196,
        "distance": 4.91039648084335,
        "above": true,
        "bars": 42
      },
      "vwapM": {
        "vwap": 0.5791643367750372,
        "distance": -0.8916876346001971,
        "above": false,
        "bars": 130
      },
      "delta": {
        "lastDelta": -444101.8999999901,
        "cumDelta": 2961.399999999441,
        "ratio": 0.0002812562029937198,
        "bars": 3
      }
    }
  },
  "INJ": {
    "label": "NEUTRAL_weak",
    "bias": "SHORT CROWDED",
    "signal": "PIATTO",
    "ts": 1783192985,
    "since_ts": 1783165169,
    "confluence": {
      "score": 10,
      "total": 17
    },
    "data": {
      "price": 4.85,
      "px24h": -0.3083247687564351,
      "px4h": -0.20576131687244187,
      "oi24h": -1.1162667597454978,
      "oi4h": 0.31412069653823177,
      "funding": -0.3055,
      "lsr": 0.8116,
      "lsrSource": "coinalyze",
      "trend": {
        "label": "TREND UP",
        "emaFast": 4.807229408235499,
        "emaSlow": 4.733518980828394,
        "emaMacro": 4.733518980828394,
        "emaMacroPeriod": 50,
        "fastVsSlow": true,
        "aboveMacro": true
      },
      "obv": {
        "obvChange": 29.667405633341964,
        "priceChange": 3.3829787234042508,
        "diverge": false,
        "direction": 1
      },
      "rvol": {
        "ratio": 0.6487108503579735,
        "current": 741777.3999999911,
        "avg": 1143463.839999996
      },
      "fvg": {
        "above": {
          "type": "bear",
          "top": 5.216,
          "bottom": 5.137,
          "size": 1.537862565699837,
          "distance": 5.917525773195875
        },
        "below": {
          "type": "bull",
          "top": 4.686,
          "bottom": 4.671,
          "size": 0.3211303789338403,
          "distance": -3.381443298969066
        },
        "count": 4
      },
      "poc": {
        "poc": 4.5942,
        "vah": 5.314559999999999,
        "val": 4.29144,
        "rangeHigh": 6.108,
        "rangeLow": 4.02,
        "distance": -5.274226804123708,
        "inValueArea": true
      },
      "vwapW": {
        "vwap": 4.6893500011616895,
        "distance": 3.6177721602414654,
        "above": true,
        "bars": 42
      },
      "vwapM": {
        "vwap": 4.92371524496006,
        "distance": -1.3143579947338084,
        "above": false,
        "bars": 130
      },
      "delta": {
        "lastDelta": -45976.19999998971,
        "cumDelta": -94471.9999999823,
        "ratio": -0.040266772053373104,
        "bars": 3
      }
    }
  },
  "SEI": {
    "label": "NEUTRAL_weak",
    "bias": "SHORT CROWDED",
    "signal": "PIATTO",
    "ts": 1783192985,
    "since_ts": 1783177934,
    "confluence": {
      "score": 0,
      "total": 0
    },
    "data": {
      "price": 0.05029,
      "px24h": 0.7210094131784482,
      "px4h": 0.39928129367138904,
      "oi24h": -5.091782303950887,
      "oi4h": -0.5410302113016402,
      "funding": -0.34259999999999996,
      "lsr": 0.9109,
      "lsrSource": "coinalyze",
      "trend": {
        "label": "PULLBACK UP",
        "emaFast": 0.04950228901417341,
        "emaSlow": 0.049912551388930866,
        "emaMacro": 0.049912551388930866,
        "emaMacroPeriod": 50,
        "fastVsSlow": false,
        "aboveMacro": true
      },
      "obv": {
        "obvChange": 12.266110197897587,
        "priceChange": -4.748391978811953,
        "diverge": true,
        "direction": 1
      },
      "rvol": {
        "ratio": 0.788096999025289,
        "current": 34864304.0,
        "avg": 44238595.05
      },
      "fvg": {
        "above": {
          "type": "bear",
          "top": 0.0513,
          "bottom": 0.05081,
          "size": 0.9643770911237893,
          "distance": 1.034002783853648
        },
        "below": {
          "type": "bull",
          "top": 0.04837,
          "bottom": 0.04831,
          "size": 0.12419788863590249,
          "distance": -3.817856432690392
        },
        "count": 4
      },
      "poc": {
        "poc": 0.05457025,
        "vah": 0.058909,
        "val": 0.051165999999999996,
        "rangeHigh": 0.05971,
        "rangeLow": 0.04636,
        "distance": 8.511135414595346,
        "inValueArea": false
      },
      "vwapW": {
        "vwap": 0.04893280827906367,
        "distance": 2.8961994432326246,
        "above": true,
        "bars": 42
      },
      "vwapM": {
        "vwap": 0.05301744219384803,
        "distance": -5.031254024090877,
        "above": false,
        "bars": 130
      },
      "delta": {
        "lastDelta": 690330.0,
        "cumDelta": 833800.0,
        "ratio": 0.008188175708626802,
        "bars": 3
      }
    }
  },
  "ONDO": {
    "label": "NEUTRAL_weak",
    "bias": "LONG CROWDED",
    "signal": "PARZIALE",
    "ts": 1783192985,
    "since_ts": 1783157387,
    "confluence": {
      "score": 7,
      "total": 17
    },
    "data": {
      "price": 0.343,
      "px24h": 2.3880597014925393,
      "px4h": 2.0529604284439205,
      "oi24h": 1.8622430218725168,
      "oi4h": 0.9186656949078035,
      "funding": 0.5,
      "lsr": 1.3036,
      "lsrSource": "coinalyze",
      "trend": {
        "label": "TREND UP",
        "emaFast": 0.33380900767803323,
        "emaSlow": 0.3256530745032885,
        "emaMacro": 0.3256530745032885,
        "emaMacroPeriod": 50,
        "fastVsSlow": true,
        "aboveMacro": true
      },
      "obv": {
        "obvChange": -7.720135013017804,
        "priceChange": 9.044747699143137,
        "diverge": true,
        "direction": -1
      },
      "rvol": {
        "ratio": 1.4391290248816326,
        "current": 37411905.500000104,
        "avg": 25996213.58000003
      },
      "fvg": {
        "above": null,
        "below": {
          "type": "bull",
          "top": 0.3348,
          "bottom": 0.3344,
          "size": 0.11961722488038622,
          "distance": -2.390670553935872
        },
        "count": 2
      },
      "poc": {
        "poc": 0.312466,
        "vah": 0.359396,
        "val": 0.29616400000000004,
        "rangeHigh": 0.392,
        "rangeLow": 0.2932,
        "distance": -8.902040816326531,
        "inValueArea": true
      },
      "vwapW": {
        "vwap": 0.32219826483362085,
        "distance": 6.642411676993591,
        "above": true,
        "bars": 42
      },
      "vwapM": {
        "vwap": 0.33970895838896875,
        "distance": 1.1454044749023073,
        "above": true,
        "bars": 130
      },
      "delta": {
        "lastDelta": 325707.6999999136,
        "cumDelta": -2345370.5000001937,
        "ratio": -0.032476987053268416,
        "bars": 3
      }
    }
  },
  "ENA": {
    "label": "LONG_moderate",
    "bias": "LONG CROWDED",
    "signal": "PIATTO",
    "ts": 1783192985,
    "since_ts": 1783177934,
    "confluence": {
      "score": 8,
      "total": 17
    },
    "data": {
      "price": 0.07987,
      "px24h": 1.3064434297311052,
      "px4h": -1.1754516208859271,
      "oi24h": -1.5137441193888566,
      "oi4h": -0.17479191704390515,
      "funding": 0.5,
      "lsr": 1.2619,
      "lsrSource": "coinalyze",
      "trend": {
        "label": "TREND UP",
        "emaFast": 0.07837725349050238,
        "emaSlow": 0.07798012786414005,
        "emaMacro": 0.07798012786414005,
        "emaMacroPeriod": 50,
        "fastVsSlow": true,
        "aboveMacro": true
      },
      "obv": {
        "obvChange": 128.77308568202605,
        "priceChange": 2.3699718165513586,
        "diverge": false,
        "direction": 1
      },
      "rvol": {
        "ratio": 0.7170345735860963,
        "current": 152562494.0,
        "avg": 212768672.0
      },
      "fvg": {
        "above": {
          "type": "bear",
          "top": 0.08977,
          "bottom": 0.08739,
          "size": 2.723423732692536,
          "distance": 9.415299862276198
        },
        "below": {
          "type": "bull",
          "top": 0.07962,
          "bottom": 0.07834,
          "size": 1.6339034975746611,
          "distance": -0.31300863903843773
        },
        "count": 5
      },
      "poc": {
        "poc": 0.07847145,
        "vah": 0.0905032,
        "val": 0.0752158,
        "rangeHigh": 0.09843,
        "rangeLow": 0.07012,
        "distance": -1.7510329285088249,
        "inValueArea": true
      },
      "vwapW": {
        "vwap": 0.07638979932365422,
        "distance": 4.6082077810299165,
        "above": true,
        "bars": 42
      },
      "vwapM": {
        "vwap": 0.08346463900106943,
        "distance": -4.258856257706799,
        "above": false,
        "bars": 130
      },
      "delta": {
        "lastDelta": -4237834.0,
        "cumDelta": -10933362.0,
        "ratio": -0.020698537459061018,
        "bars": 3
      }
    }
  },
  "JUP": {
    "label": "NEUTRAL_weak",
    "bias": "BEAR EXHAUSTION",
    "signal": "PARZIALE",
    "ts": 1783192985,
    "since_ts": 1783100417,
    "confluence": {
      "score": 9,
      "total": 17
    },
    "data": {
      "price": 0.2344,
      "px24h": -4.2874642711310775,
      "px4h": -1.0135135135135191,
      "oi24h": -6.207369207413553,
      "oi4h": -1.0258676174806347,
      "funding": -0.49760000000000004,
      "lsr": 1.2036,
      "lsrSource": "coinalyze",
      "trend": {
        "label": "TREND UP",
        "emaFast": 0.23801448434238498,
        "emaSlow": 0.22811946359940277,
        "emaMacro": 0.22811946359940277,
        "emaMacroPeriod": 50,
        "fastVsSlow": true,
        "aboveMacro": true
      },
      "obv": {
        "obvChange": -1839.6473238990945,
        "priceChange": 2.7097902097902025,
        "diverge": true,
        "direction": -1
      },
      "rvol": {
        "ratio": 0.4363352175589387,
        "current": 8219951.0,
        "avg": 18838614.6
      },
      "fvg": {
        "above": {
          "type": "bear",
          "top": 0.2397,
          "bottom": 0.2381,
          "size": 0.6719865602687904,
          "distance": 1.578498293515362
        },
        "below": {
          "type": "bull",
          "top": 0.2314,
          "bottom": 0.2249,
          "size": 2.890173410404627,
          "distance": -1.2798634812286702
        },
        "count": 8
      },
      "poc": {
        "poc": 0.21832700000000002,
        "vah": 0.22742,
        "val": 0.18585200000000002,
        "rangeHigh": 0.2534,
        "rangeLow": 0.1668,
        "distance": -6.857081911262789,
        "inValueArea": false
      },
      "vwapW": {
        "vwap": 0.2286073226504547,
        "distance": 2.7963572100093357,
        "above": true,
        "bars": 42
      },
      "vwapM": {
        "vwap": 0.21267863241576937,
        "distance": 10.495350346523841,
        "above": true,
        "bars": 130
      },
      "delta": {
        "lastDelta": -677977.0,
        "cumDelta": -2777967.0,
        "ratio": -0.08413049030275556,
        "bars": 3
      }
    }
  },
  "BONK": {
    "label": "LONG_moderate",
    "bias": "OVERHEATED LONG",
    "signal": "PIATTO",
    "ts": 1783192985,
    "since_ts": 1783165169,
    "confluence": {
      "score": 9,
      "total": 17
    },
    "data": {
      "price": 0.004957,
      "px24h": 9.064906490649046,
      "px4h": -0.7408890668802678,
      "oi24h": 10.361235103268944,
      "oi4h": 1.5149849820348384,
      "funding": 0.455,
      "lsr": 1.8686,
      "lsrSource": "coinalyze",
      "trend": {
        "label": "TREND UP",
        "emaFast": 0.004756097054773287,
        "emaSlow": 0.004446018696405626,
        "emaMacro": 0.004446018696405626,
        "emaMacroPeriod": 50,
        "fastVsSlow": true,
        "aboveMacro": true
      },
      "obv": {
        "obvChange": 71.13512495967473,
        "priceChange": 18.964277151762168,
        "diverge": false,
        "direction": 1
      },
      "rvol": {
        "ratio": 1.0961504727883256,
        "current": 1183218198.0,
        "avg": 1079430449.9
      },
      "fvg": {
        "above": null,
        "below": {
          "type": "bull",
          "top": 0.004816,
          "bottom": 0.004583,
          "size": 5.084006109535232,
          "distance": -2.8444623764373542
        },
        "count": 4
      },
      "poc": {
        "poc": 0.0041724250000000004,
        "vah": 0.00471345,
        "val": 0.0040514900000000005,
        "rangeHigh": 0.005159,
        "rangeLow": 0.003886,
        "distance": -15.827617510591068,
        "inValueArea": false
      },
      "vwapW": {
        "vwap": 0.00448943664479967,
        "distance": 10.526117029577051,
        "above": true,
        "bars": 42
      },
      "vwapM": {
        "vwap": 0.004486107739651207,
        "distance": 10.608132661249764,
        "above": true,
        "bars": 130
      },
      "delta": {
        "lastDelta": -18649542.0,
        "cumDelta": 21326174.0,
        "ratio": 0.0053958970537775625,
        "bars": 3
      }
    }
  },
  "PENGU": {
    "label": "LONG_moderate",
    "bias": "LONG CROWDED",
    "signal": "PIATTO",
    "ts": 1783192985,
    "since_ts": 1783185242,
    "confluence": {
      "score": 9,
      "total": 17
    },
    "data": {
      "price": 0.006768,
      "px24h": 0.16279413941097715,
      "px4h": -1.1393514460999117,
      "oi24h": 1.4604209810979434,
      "oi4h": -1.121794597615262,
      "funding": 0.5,
      "lsr": 1.318,
      "lsrSource": "coinalyze",
      "trend": {
        "label": "TREND UP",
        "emaFast": 0.006666973198665299,
        "emaSlow": 0.006411327924285941,
        "emaMacro": 0.006411327924285941,
        "emaMacroPeriod": 50,
        "fastVsSlow": true,
        "aboveMacro": true
      },
      "obv": {
        "obvChange": 59.62896889262366,
        "priceChange": 11.85405316163117,
        "diverge": false,
        "direction": 1
      },
      "rvol": {
        "ratio": 0.5410753320277915,
        "current": 519805528.0,
        "avg": 960689754.7
      },
      "fvg": {
        "above": null,
        "below": {
          "type": "bull",
          "top": 0.006678,
          "bottom": 0.006517,
          "size": 2.470461868958105,
          "distance": -1.3297872340425503
        },
        "count": 3
      },
      "poc": {
        "poc": 0.006228475,
        "vah": 0.0068638499999999995,
        "val": 0.00596455,
        "rangeHigh": 0.007509,
        "rangeLow": 0.005554,
        "distance": -7.971705082742315,
        "inValueArea": true
      },
      "vwapW": {
        "vwap": 0.006365817663648376,
        "distance": 6.427804847258432,
        "above": true,
        "bars": 42
      },
      "vwapM": {
        "vwap": 0.0064973241000269985,
        "distance": 4.273696304788728,
        "above": true,
        "bars": 130
      },
      "delta": {
        "lastDelta": 14534314.0,
        "cumDelta": -23137580.0,
        "ratio": -0.010557739692935202,
        "bars": 3
      }
    }
  },
  "KAS": {
    "label": "NEUTRAL_weak",
    "bias": "LONG CROWDED",
    "signal": "PARZIALE",
    "ts": 1783192985,
    "since_ts": 1783165169,
    "confluence": {
      "score": 8,
      "total": 17
    },
    "data": {
      "price": 0.03098,
      "px24h": -0.44987146529562266,
      "px4h": -0.7051282051281986,
      "oi24h": -2.6612312819340413,
      "oi4h": 0.08143399918049156,
      "funding": 0.496,
      "lsr": 2.39097999321804,
      "lsrSource": "coinalyze",
      "trend": {
        "label": "TREND UP",
        "emaFast": 0.03107375532995655,
        "emaSlow": 0.030217742217949494,
        "emaMacro": 0.030217742217949494,
        "emaMacroPeriod": 50,
        "fastVsSlow": true,
        "aboveMacro": true
      },
      "obv": {
        "obvChange": 84.25608189338435,
        "priceChange": 10.152644657436982,
        "diverge": false,
        "direction": 1
      },
      "rvol": {
        "ratio": 0.7973208770629235,
        "current": 8086290.0,
        "avg": 10141826.5
      },
      "fvg": {
        "above": {
          "type": "bear",
          "top": 0.03375,
          "bottom": 0.03297,
          "size": 2.3657870791628843,
          "distance": 6.423499031633308
        },
        "below": {
          "type": "bull",
          "top": 0.02998,
          "bottom": 0.02952,
          "size": 1.5582655826558218,
          "distance": -3.2278889606197576
        },
        "count": 3
      },
      "poc": {
        "poc": 0.02996035,
        "vah": 0.0319914,
        "val": 0.027929299999999997,
        "rangeHigh": 0.03481,
        "rangeLow": 0.02652,
        "distance": -3.291316978695934,
        "inValueArea": true
      },
      "vwapW": {
        "vwap": 0.03011620817542038,
        "distance": 3.034219378671371,
        "above": true,
        "bars": 42
      },
      "vwapM": {
        "vwap": 0.030184555772168067,
        "distance": 2.800916582020665,
        "above": true,
        "bars": 130
      },
      "delta": {
        "lastDelta": -88670.0,
        "cumDelta": -3198330.0,
        "ratio": -0.12892172018166492,
        "bars": 3
      }
    }
  },
  "TRX": {
    "label": "LONG_strong",
    "bias": "LONG CROWDED",
    "signal": "PIATTO",
    "ts": 1783192985,
    "since_ts": 1783185242,
    "confluence": {
      "score": 12,
      "total": 17
    },
    "data": {
      "price": 0.32597,
      "px24h": 1.522984925875173,
      "px4h": 0.08904446082042401,
      "oi24h": -6.162680115017986,
      "oi4h": -0.22627746222601336,
      "funding": 0.9629000000000001,
      "lsr": 1.1844,
      "lsrSource": "coinalyze",
      "trend": {
        "label": "TREND UP",
        "emaFast": 0.32269879891213604,
        "emaSlow": 0.32097563841039756,
        "emaMacro": 0.32097563841039756,
        "emaMacroPeriod": 50,
        "fastVsSlow": true,
        "aboveMacro": true
      },
      "obv": {
        "obvChange": 87.23460726133304,
        "priceChange": 1.8653335416341117,
        "diverge": false,
        "direction": 1
      },
      "rvol": {
        "ratio": 0.6509692657095317,
        "current": 14033869.0,
        "avg": 21558420.25
      },
      "fvg": {
        "above": {
          "type": "bear",
          "top": 0.33277,
          "bottom": 0.33168,
          "size": 0.3286300048239374,
          "distance": 1.7516949412522602
        },
        "below": {
          "type": "bull",
          "top": 0.32498,
          "bottom": 0.32393,
          "size": 0.32414410520791387,
          "distance": -0.30370893026965395
        },
        "count": 6
      },
      "poc": {
        "poc": 0.32103875000000004,
        "vah": 0.3249875,
        "val": 0.31547000000000003,
        "rangeHigh": 0.3341,
        "rangeLow": 0.31385,
        "distance": -1.512792588274977,
        "inValueArea": false
      },
      "vwapW": {
        "vwap": 0.31986326236868456,
        "distance": 1.92480298791518,
        "above": true,
        "bars": 42
      },
      "vwapM": {
        "vwap": 0.32225251031530705,
        "distance": 1.1691110430781864,
        "above": true,
        "bars": 130
      },
      "delta": {
        "lastDelta": 2230915.0,
        "cumDelta": 8046970.0,
        "ratio": 0.1476001324902761,
        "bars": 3
      }
    }
  },
  "ROSE": {
    "label": "LONG_moderate",
    "bias": "LONG CROWDED",
    "signal": "PARZIALE",
    "ts": 1783192985,
    "since_ts": 1783172646,
    "confluence": {
      "score": 8,
      "total": 17
    },
    "data": {
      "price": 0.006133,
      "px24h": -0.4221464523461597,
      "px4h": -0.8727978018425628,
      "oi24h": -0.48977799264560784,
      "oi4h": -0.24162186361012628,
      "funding": 1.0,
      "lsr": 1.9283,
      "lsrSource": "coinalyze",
      "trend": {
        "label": "TREND UP",
        "emaFast": 0.006066589717288179,
        "emaSlow": 0.00597229855715045,
        "emaMacro": 0.00597229855715045,
        "emaMacroPeriod": 50,
        "fastVsSlow": true,
        "aboveMacro": true
      },
      "obv": {
        "obvChange": 152.3713083502588,
        "priceChange": 2.093370991859117,
        "diverge": false,
        "direction": 1
      },
      "rvol": {
        "ratio": 0.5103458493933561,
        "current": 31900655.0,
        "avg": 62507915.05
      },
      "fvg": {
        "above": {
          "type": "bear",
          "top": 0.006677,
          "bottom": 0.00662,
          "size": 0.8610271903323227,
          "distance": 7.9406489483124005
        },
        "below": {
          "type": "bull",
          "top": 0.006101,
          "bottom": 0.005924,
          "size": 2.9878460499662403,
          "distance": -0.5217674873634564
        },
        "count": 2
      },
      "poc": {
        "poc": 0.00585297,
        "vah": 0.00686944,
        "val": 0.00559606,
        "rangeHigh": 0.007629,
        "rangeLow": 0.005395,
        "distance": -4.565954671449544,
        "inValueArea": true
      },
      "vwapW": {
        "vwap": 0.005891477956963042,
        "distance": 4.303199382038338,
        "above": true,
        "bars": 42
      },
      "vwapM": {
        "vwap": 0.006476590670575667,
        "distance": -5.119833681664392,
        "above": false,
        "bars": 130
      },
      "delta": {
        "lastDelta": 2276409.0,
        "cumDelta": -381003.0,
        "ratio": -0.0030889350168020933,
        "bars": 3
      }
    }
  },
  "NEAR": {
    "label": "LONG_moderate",
    "bias": "SHORT CROWDED",
    "signal": "CONFERMA",
    "ts": 1783192985,
    "since_ts": 1783172646,
    "confluence": {
      "score": 10,
      "total": 17
    },
    "data": {
      "price": 2.003,
      "px24h": -0.24900398406373972,
      "px4h": -1.6208251473477364,
      "oi24h": -2.5146915661050504,
      "oi4h": -1.6816894972017653,
      "funding": -0.0416,
      "lsr": 1.164,
      "lsrSource": "coinalyze",
      "trend": {
        "label": "TREND UP",
        "emaFast": 1.9857917907309057,
        "emaSlow": 1.9342279050587605,
        "emaMacro": 1.9342279050587605,
        "emaMacroPeriod": 50,
        "fastVsSlow": true,
        "aboveMacro": true
      },
      "obv": {
        "obvChange": 30.623688951100466,
        "priceChange": 11.265260821309647,
        "diverge": false,
        "direction": 1
      },
      "rvol": {
        "ratio": 0.9532276912213441,
        "current": 13207940.0,
        "avg": 13856017.95
      },
      "fvg": {
        "above": {
          "type": "bear",
          "top": 2.421,
          "bottom": 2.359,
          "size": 2.6282323018227993,
          "distance": 17.773339990014968
        },
        "below": {
          "type": "bull",
          "top": 1.99,
          "bottom": 1.983,
          "size": 0.3530005042864294,
          "distance": -0.6490264603095418
        },
        "count": 3
      },
      "poc": {
        "poc": 1.842945,
        "vah": 2.18355,
        "val": 1.76305,
        "rangeHigh": 2.562,
        "rangeLow": 1.721,
        "distance": -7.990763854218674,
        "inValueArea": true
      },
      "vwapW": {
        "vwap": 1.900402773786695,
        "distance": 5.503950407570022,
        "above": true,
        "bars": 42
      },
      "vwapM": {
        "vwap": 2.0674277095711227,
        "distance": -3.0195836730887713,
        "above": false,
        "bars": 130
      },
      "delta": {
        "lastDelta": -671262.0,
        "cumDelta": 107854.0,
        "ratio": 0.0025982101465244632,
        "bars": 3
      }
    }
  },
  "FET": {
    "label": "LONG_moderate",
    "bias": "LONG CROWDED",
    "signal": "PIATTO",
    "ts": 1783192985,
    "since_ts": 1783185242,
    "confluence": {
      "score": 8,
      "total": 17
    },
    "data": {
      "price": 0.187,
      "px24h": -0.795755968169762,
      "px4h": 0.3757380568974805,
      "oi24h": -1.1272977010111815,
      "oi4h": -1.043610441632577,
      "funding": 1.0,
      "lsr": 1.2925,
      "lsrSource": "coinalyze",
      "trend": {
        "label": "TREND UP",
        "emaFast": 0.18528736156575187,
        "emaSlow": 0.18108622160379118,
        "emaMacro": 0.18108622160379118,
        "emaMacroPeriod": 50,
        "fastVsSlow": true,
        "aboveMacro": true
      },
      "obv": {
        "obvChange": 100.67216616075676,
        "priceChange": 7.524411257897761,
        "diverge": false,
        "direction": 1
      },
      "rvol": {
        "ratio": 1.0578639671204777,
        "current": 30393105.0,
        "avg": 28730636.4
      },
      "fvg": {
        "above": {
          "type": "bear",
          "top": 0.2033,
          "bottom": 0.203,
          "size": 0.14778325123152447,
          "distance": 8.556149732620328
        },
        "below": {
          "type": "bull",
          "top": 0.1824,
          "bottom": 0.1806,
          "size": 0.996677740863785,
          "distance": -2.4598930481283388
        },
        "count": 2
      },
      "poc": {
        "poc": 0.1737425,
        "vah": 0.196214,
        "val": 0.163298,
        "rangeHigh": 0.2228,
        "rangeLow": 0.1595,
        "distance": -7.089572192513371,
        "inValueArea": true
      },
      "vwapW": {
        "vwap": 0.1792657827047279,
        "distance": 4.425951888621549,
        "above": true,
        "bars": 42
      },
      "vwapM": {
        "vwap": 0.18816445984349142,
        "distance": -0.51256217263006,
        "above": false,
        "bars": 130
      },
      "delta": {
        "lastDelta": -2103145.0,
        "cumDelta": 477765.0,
        "ratio": 0.0060972879132167555,
        "bars": 3
      }
    }
  },
  "HYPE": {
    "label": "NEUTRAL_weak",
    "bias": "LONG CROWDED",
    "signal": "PARZIALE",
    "ts": 1783192985,
    "since_ts": 1783185242,
    "confluence": {
      "score": 9,
      "total": 17
    },
    "data": {
      "price": 69.883,
      "px24h": -0.5677129279189564,
      "px4h": -1.080032839792777,
      "oi24h": 0.008709565363164154,
      "oi4h": -0.6984834768001509,
      "funding": 0.5,
      "lsr": 1.1468,
      "lsrSource": "coinalyze",
      "trend": {
        "label": "TREND UP",
        "emaFast": 69.41391994281008,
        "emaSlow": 66.45526050603313,
        "emaMacro": 66.45526050603313,
        "emaMacroPeriod": 50,
        "fastVsSlow": true,
        "aboveMacro": true
      },
      "obv": {
        "obvChange": 70.93941607988563,
        "priceChange": 7.6923076923076845,
        "diverge": false,
        "direction": 1
      },
      "rvol": {
        "ratio": 0.7231842163468315,
        "current": 1324326.5299999937,
        "avg": 1831243.6860000007
      },
      "fvg": {
        "above": null,
        "below": {
          "type": "bull",
          "top": 68.751,
          "bottom": 67.82,
          "size": 1.3727514007667527,
          "distance": -1.6198503212512212
        },
        "count": 3
      },
      "poc": {
        "poc": 63.03105,
        "vah": 70.70439999999999,
        "val": 61.459399999999995,
        "rangeHigh": 76.991,
        "rangeLow": 58.501,
        "distance": -9.804888170227374,
        "inValueArea": true
      },
      "vwapW": {
        "vwap": 65.44495404786494,
        "distance": 6.746197650174827,
        "above": true,
        "bars": 42
      },
      "vwapM": {
        "vwap": 66.73296985152177,
        "distance": 4.685884886339909,
        "above": true,
        "bars": 130
      },
      "delta": {
        "lastDelta": -106360.30999999284,
        "cumDelta": -205410.41999995196,
        "ratio": -0.05839120890635147,
        "bars": 3
      }
    }
  },
  "STRK": {
    "label": "NEUTRAL_weak",
    "bias": "LONG CROWDED",
    "signal": "PIATTO",
    "ts": 1783192985,
    "since_ts": 1783148007,
    "confluence": {
      "score": 6,
      "total": 17
    },
    "data": {
      "price": 0.03166,
      "px24h": 0.7317849188673275,
      "px4h": 0.25332488917037266,
      "oi24h": -2.770626679107325,
      "oi4h": -0.311356598550449,
      "funding": 0.32239999999999996,
      "lsr": 1.4857,
      "lsrSource": "coinalyze",
      "trend": {
        "label": "TREND UP",
        "emaFast": 0.0312477286949713,
        "emaSlow": 0.030670474481798306,
        "emaMacro": 0.030670474481798306,
        "emaMacroPeriod": 50,
        "fastVsSlow": true,
        "aboveMacro": true
      },
      "obv": {
        "obvChange": -15.638694433566155,
        "priceChange": 8.236500341763483,
        "diverge": true,
        "direction": -1
      },
      "rvol": {
        "ratio": 0.6124993130754731,
        "current": 19091213.49999998,
        "avg": 31169363.119999994
      },
      "fvg": {
        "above": {
          "type": "bear",
          "top": 0.03305,
          "bottom": 0.03281,
          "size": 0.7314843035659985,
          "distance": 3.632343651295004
        },
        "below": {
          "type": "bull",
          "top": 0.03142,
          "bottom": 0.03133,
          "size": 0.28726460261729914,
          "distance": -0.7580543272267976
        },
        "count": 5
      },
      "poc": {
        "poc": 0.02967925,
        "vah": 0.0341782,
        "val": 0.0281122,
        "rangeHigh": 0.03802,
        "rangeLow": 0.02791,
        "distance": -6.2563171193935565,
        "inValueArea": true
      },
      "vwapW": {
        "vwap": 0.029946638112217774,
        "distance": 5.754775815984222,
        "above": true,
        "bars": 42
      },
      "vwapM": {
        "vwap": 0.032056372943184544,
        "distance": -1.2052921391616558,
        "above": false,
        "bars": 130
      },
      "delta": {
        "lastDelta": -1566867.8999999575,
        "cumDelta": -3842658.999999903,
        "ratio": -0.053621877847954406,
        "bars": 3
      }
    }
  },
  "XLM": {
    "label": "LONG_moderate",
    "bias": "LONG CROWDED",
    "signal": "PIATTO",
    "ts": 1783192985,
    "since_ts": 1782997495,
    "confluence": {
      "score": 9,
      "total": 17
    },
    "data": {
      "price": 0.21053,
      "px24h": 3.368193646585165,
      "px4h": -0.4068309759212828,
      "oi24h": -2.2575155552649977,
      "oi4h": -1.3185657265978674,
      "funding": 0.777,
      "lsr": 1.0665,
      "lsrSource": "coinalyze",
      "trend": {
        "label": "TREND UP",
        "emaFast": 0.20467349546770472,
        "emaSlow": 0.19508522799793185,
        "emaMacro": 0.19508522799793185,
        "emaMacroPeriod": 50,
        "fastVsSlow": true,
        "aboveMacro": true
      },
      "obv": {
        "obvChange": 49.13174754556867,
        "priceChange": 18.14251221292605,
        "diverge": false,
        "direction": 1
      },
      "rvol": {
        "ratio": 1.1279340897472823,
        "current": 113183335.0,
        "avg": 100345699.3
      },
      "fvg": {
        "above": {
          "type": "bear",
          "top": 0.22541,
          "bottom": 0.22134,
          "size": 1.8388000361434853,
          "distance": 5.134660143447496
        },
        "below": {
          "type": "bull",
          "top": 0.1965,
          "bottom": 0.18917,
          "size": 3.874821589046891,
          "distance": -6.664133377665885
        },
        "count": 4
      },
      "poc": {
        "poc": 0.20063730000000002,
        "vah": 0.22013760000000002,
        "val": 0.1711794,
        "rangeHigh": 0.25167,
        "rangeLow": 0.16869,
        "distance": -4.698950268370292,
        "inValueArea": true
      },
      "vwapW": {
        "vwap": 0.1935799819853628,
        "distance": 8.688924258660698,
        "above": true,
        "bars": 42
      },
      "vwapM": {
        "vwap": 0.20614133710600607,
        "distance": 2.0658946690560938,
        "above": true,
        "bars": 130
      },
      "delta": {
        "lastDelta": -4188799.0,
        "cumDelta": -8558493.0,
        "ratio": -0.029048896139177077,
        "bars": 3
      }
    }
  },
  "ZEC": {
    "label": "LONG_moderate",
    "bias": "LONG CROWDED",
    "signal": "PARZIALE",
    "ts": 1783192985,
    "since_ts": 1783083730,
    "confluence": {
      "score": 9,
      "total": 17
    },
    "data": {
      "price": 471.68,
      "px24h": 2.4878864915368375,
      "px4h": 1.3711583924349873,
      "oi24h": -2.3021913646020375,
      "oi4h": -0.21310353396204476,
      "funding": 1.0,
      "lsr": 0.7702,
      "lsrSource": "coinalyze",
      "trend": {
        "label": "TREND UP",
        "emaFast": 455.7237531886488,
        "emaSlow": 430.12838872769345,
        "emaMacro": 430.12838872769345,
        "emaMacroPeriod": 50,
        "fastVsSlow": true,
        "aboveMacro": true
      },
      "obv": {
        "obvChange": 54.50814963241173,
        "priceChange": 15.156615925058547,
        "diverge": false,
        "direction": 1
      },
      "rvol": {
        "ratio": 0.5741161360025677,
        "current": 127196.53100000067,
        "avg": 221551.91785000064
      },
      "fvg": {
        "above": {
          "type": "bear",
          "top": 518.67,
          "bottom": 516.69,
          "size": 0.38320850026126,
          "distance": 9.542486431478979
        },
        "below": {
          "type": "bull",
          "top": 452.66,
          "bottom": 441.3,
          "size": 2.5742125538182674,
          "distance": -4.032394843962004
        },
        "count": 4
      },
      "poc": {
        "poc": 418.07534999999996,
        "vah": 471.91089999999997,
        "val": 380.1257,
        "rangeHigh": 544.28,
        "rangeLow": 367.77,
        "distance": -11.364622201492548,
        "inValueArea": true
      },
      "vwapW": {
        "vwap": 416.8482688600256,
        "distance": 13.242643730040468,
        "above": true,
        "bars": 42
      },
      "vwapM": {
        "vwap": 445.91499815349965,
        "distance": 5.860982912600704,
        "above": true,
        "bars": 130
      },
      "delta": {
        "lastDelta": -1679.9750000006898,
        "cumDelta": 4829.871000001091,
        "ratio": 0.010511780530832094,
        "bars": 3
      }
    }
  },
  "ALGO": {
    "label": "LONG_moderate",
    "bias": "LONG CROWDED",
    "signal": "PIATTO",
    "ts": 1783192985,
    "since_ts": 1783172646,
    "confluence": {
      "score": 9,
      "total": 17
    },
    "data": {
      "price": 0.091,
      "px24h": 0.9988901220865684,
      "px4h": 0.11001100110011316,
      "oi24h": -7.5301997733219554,
      "oi4h": -1.2656053289951539,
      "funding": 1.0,
      "lsr": 1.265,
      "lsrSource": "coinalyze",
      "trend": {
        "label": "TREND UP",
        "emaFast": 0.08897191337484318,
        "emaSlow": 0.0874377749725439,
        "emaMacro": 0.0874377749725439,
        "emaMacroPeriod": 50,
        "fastVsSlow": true,
        "aboveMacro": true
      },
      "obv": {
        "obvChange": 388.1864585501951,
        "priceChange": 8.333333333333323,
        "diverge": false,
        "direction": 1
      },
      "rvol": {
        "ratio": 0.9095800765875691,
        "current": 22411696.7,
        "avg": 24639608.185000006
      },
      "fvg": {
        "above": {
          "type": "bear",
          "top": 0.0938,
          "bottom": 0.0927,
          "size": 1.186623516720593,
          "distance": 1.8681318681318761
        },
        "below": {
          "type": "bull",
          "top": 0.0903,
          "bottom": 0.0895,
          "size": 0.8938547486033621,
          "distance": -0.7692307692307607
        },
        "count": 3
      },
      "poc": {
        "poc": 0.0904025,
        "vah": 0.096111,
        "val": 0.08516,
        "rangeHigh": 0.1038,
        "rangeLow": 0.0805,
        "distance": -0.6565934065934075,
        "inValueArea": true
      },
      "vwapW": {
        "vwap": 0.08654234297034269,
        "distance": 5.150839319412589,
        "above": true,
        "bars": 42
      },
      "vwapM": {
        "vwap": 0.09098147163534712,
        "distance": 0.020364986760318202,
        "above": true,
        "bars": 130
      },
      "delta": {
        "lastDelta": -93567.89999998361,
        "cumDelta": 3434963.3000000343,
        "ratio": 0.06050988939718718,
        "bars": 3
      }
    }
  },
  "APT": {
    "label": "LONG_moderate",
    "bias": "SHORT SQUEEZE",
    "signal": "PIATTO",
    "ts": 1783192985,
    "since_ts": 1783185242,
    "confluence": {
      "score": 9,
      "total": 17
    },
    "data": {
      "price": 0.6377,
      "px24h": 2.3759833039011133,
      "px4h": 0.06276478895340766,
      "oi24h": -5.441358322761279,
      "oi4h": -0.4005379936987733,
      "funding": 0.7628,
      "lsr": 1.3646,
      "lsrSource": "coinalyze",
      "trend": {
        "label": "TREND UP",
        "emaFast": 0.625186938493272,
        "emaSlow": 0.6095828790562735,
        "emaMacro": 0.6095828790562735,
        "emaMacroPeriod": 50,
        "fastVsSlow": true,
        "aboveMacro": true
      },
      "obv": {
        "obvChange": 22.306239586401126,
        "priceChange": 6.229180546302462,
        "diverge": false,
        "direction": 1
      },
      "rvol": {
        "ratio": 0.5899521528016145,
        "current": 3267195.900000003,
        "avg": 5538069.289999991
      },
      "fvg": {
        "above": {
          "type": "bear",
          "top": 0.6659,
          "bottom": 0.665,
          "size": 0.13533834586466345,
          "distance": 4.281009879253566
        },
        "below": {
          "type": "bull",
          "top": 0.6324,
          "bottom": 0.6277,
          "size": 0.748765333758153,
          "distance": -0.8311118080602293
        },
        "count": 4
      },
      "poc": {
        "poc": 0.6322215,
        "vah": 0.684839,
        "val": 0.5957939999999999,
        "rangeHigh": 0.7156,
        "rangeLow": 0.5537,
        "distance": -0.859103026501498,
        "inValueArea": true
      },
      "vwapW": {
        "vwap": 0.593481571978302,
        "distance": 7.467532289834663,
        "above": true,
        "bars": 42
      },
      "vwapM": {
        "vwap": 0.6300247061906128,
        "distance": 1.2341252228662347,
        "above": true,
        "bars": 130
      },
      "delta": {
        "lastDelta": -192920.29999999749,
        "cumDelta": -166599.09999998473,
        "ratio": -0.018725353786054316,
        "bars": 3
      }
    }
  },
  "FARTCOIN": {
    "label": "LONG_moderate",
    "bias": "LONG CROWDED",
    "signal": "PIATTO",
    "ts": 1783192985,
    "since_ts": 1783172646,
    "confluence": {
      "score": 8,
      "total": 17
    },
    "data": {
      "price": 0.1619,
      "px24h": -3.2855436081242564,
      "px4h": -1.220256253813302,
      "oi24h": -5.33010221362825,
      "oi4h": -0.3368519394290447,
      "funding": 0.5,
      "lsr": 2.0404,
      "lsrSource": "coinalyze",
      "trend": {
        "label": "TREND UP",
        "emaFast": 0.16270381418646604,
        "emaSlow": 0.14795141881617987,
        "emaMacro": 0.14795141881617987,
        "emaMacroPeriod": 50,
        "fastVsSlow": true,
        "aboveMacro": true
      },
      "obv": {
        "obvChange": 183.55127638036834,
        "priceChange": 26.385636221701798,
        "diverge": false,
        "direction": 1
      },
      "rvol": {
        "ratio": 0.6219879222930925,
        "current": 31387285.69999993,
        "avg": 50462853.98000003
      },
      "fvg": {
        "above": null,
        "below": {
          "type": "bull",
          "top": 0.1587,
          "bottom": 0.1547,
          "size": 2.5856496444731762,
          "distance": -1.9765287214329716
        },
        "count": 4
      },
      "poc": {
        "poc": 0.129514,
        "vah": 0.1437,
        "val": 0.11948,
        "rangeHigh": 0.1783,
        "rangeLow": 0.1091,
        "distance": -20.00370599135269,
        "inValueArea": false
      },
      "vwapW": {
        "vwap": 0.14986889229719605,
        "distance": 8.027755138768738,
        "above": true,
        "bars": 42
      },
      "vwapM": {
        "vwap": 0.1351230111317025,
        "distance": 19.816749674264095,
        "above": true,
        "bars": 130
      },
      "delta": {
        "lastDelta": -1793756.899999924,
        "cumDelta": 173055.5000001639,
        "ratio": 0.0021175337068399407,
        "bars": 3
      }
    }
  }
}